troveclient/__init__.py
troveclient/_i18n.py
troveclient/auth_plugin.py
troveclient/base.py
troveclient/client.py
troveclient/common.py
troveclient/exceptions.py
troveclient/extension.py
troveclient/i18n.py
troveclient/service_catalog.py
troveclient/shell.py
troveclient/utils.py
troveclient/apiclient/__init__.py
troveclient/apiclient/auth.py
troveclient/apiclient/base.py
troveclient/apiclient/client.py
troveclient/apiclient/exceptions.py
troveclient/compat/__init__.py
troveclient/compat/auth.py
troveclient/compat/base.py
troveclient/compat/cli.py
troveclient/compat/client.py
troveclient/compat/common.py
troveclient/compat/exceptions.py
troveclient/compat/mcli.py
troveclient/compat/utils.py
troveclient/compat/versions.py
troveclient/compat/tests/__init__.py
troveclient/compat/tests/test_auth.py
troveclient/compat/tests/test_common.py
troveclient/osc/__init__.py
troveclient/osc/plugin.py
troveclient/osc/v1/__init__.py
troveclient/osc/v1/base.py
troveclient/osc/v1/database_backup_strategy.py
troveclient/osc/v1/database_backups.py
troveclient/osc/v1/database_clusters.py
troveclient/osc/v1/database_configurations.py
troveclient/osc/v1/database_flavors.py
troveclient/osc/v1/database_instances.py
troveclient/osc/v1/database_limits.py
troveclient/osc/v1/database_logs.py
troveclient/osc/v1/database_quota.py
troveclient/osc/v1/database_root.py
troveclient/osc/v1/database_users.py
troveclient/osc/v1/databases.py
troveclient/osc/v1/datastores.py
troveclient/tests/__init__.py
troveclient/tests/fakes.py
troveclient/tests/test_accounts.py
troveclient/tests/test_apiclient_exceptions.py
troveclient/tests/test_backups.py
troveclient/tests/test_base.py
troveclient/tests/test_client.py
troveclient/tests/test_clusters.py
troveclient/tests/test_common.py
troveclient/tests/test_configurations.py
troveclient/tests/test_databases.py
troveclient/tests/test_datastores.py
troveclient/tests/test_discover.py
troveclient/tests/test_instances.py
troveclient/tests/test_limits.py
python_troveclient-8.9.0.dist-info/AUTHORS
python_troveclient-8.9.0.dist-info/LICENSE
python_troveclient-8.9.0.dist-info/METADATA
python_troveclient-8.9.0.dist-info/WHEEL
python_troveclient-8.9.0.dist-info/entry_points.txt
python_troveclient-8.9.0.dist-info/pbr.json
python_troveclient-8.9.0.dist-info/top_level.txt
python_troveclient-8.9.0.dist-info/RECORD
