Metadata-Version: 2.1
Name: python-troveclient
Version: 8.9.0
Summary: Client library for OpenStack DBaaS API
Home-page: https://docs.openstack.org/python-troveclient/latest
Author: OpenStack
Author-email: openstack-discuss@lists.openstack.org
Classifier: Environment :: OpenStack
Classifier: Intended Audience :: Information Technology
Classifier: Intended Audience :: System Administrators
Classifier: License :: OSI Approved :: Apache Software License
Classifier: Operating System :: POSIX :: Linux
Classifier: Programming Language :: Python
Classifier: Programming Language :: Python :: 3
Classifier: Programming Language :: Python :: 3.9
Classifier: Programming Language :: Python :: 3.10
Classifier: Programming Language :: Python :: 3.11
Classifier: Programming Language :: Python :: 3.12
Requires-Python: >=3.9
License-File: LICENSE
License-File: AUTHORS
Requires-Dist: pbr !=2.1.0,>=2.0.0
Requires-Dist: PrettyTable >=0.7.2
Requires-Dist: requests >=2.14.2
Requires-Dist: oslo.i18n >=3.15.3
Requires-Dist: oslo.utils >=3.33.0
Requires-Dist: keystoneauth1 >=3.4.0
Requires-Dist: python-swiftclient >=3.2.0
Requires-Dist: python-mistralclient !=3.2.0,>=3.1.0
Requires-Dist: osc-lib >=1.8.0
Requires-Dist: python-openstackclient >=3.12.0
Requires-Dist: stevedore >=2.0.1
